npu_easy/__init__.py
npu_easy/model.py
npu_easy/utils.py
npu_easy-0.1.0.dist-info/METADATA
npu_easy-0.1.0.dist-info/WHEEL
npu_easy-0.1.0.dist-info/top_level.txt
npu_easy-0.1.0.dist-info/RECORD
