Metadata-Version: 2.4
Name: npu-easy
Version: 0.1.0
Summary: A zero-dependency wrapper for easy NPU usage in Python on Windows.
Author: Antigravity
Classifier: Programming Language :: Python :: 3
Classifier: Operating System :: Microsoft :: Windows
Provides-Extra: intel
Requires-Dist: onnxruntime-openvino; extra == "intel"
Provides-Extra: amd
Requires-Dist: onnxruntime-directml; extra == "amd"
Provides-Extra: qualcomm
Requires-Dist: onnxruntime; extra == "qualcomm"
Dynamic: author
Dynamic: classifier
Dynamic: description
Dynamic: description-content-type
Dynamic: provides-extra
Dynamic: summary
